katana/__init__.py
katana/appmanage.py
katana/config.json
katana/dbrouter.py
katana/log.txt
katana/manage.py
katana/primary_process.py
katana/readme.md
katana/readme.txt
katana/simple_server.py
katana/user_profile.json
katana/katana_configs/app_config.json
katana/katana_configs/db.sqlite3
katana/logs/katana.django.log
katana/logs/katana.log
katana/logs/readme.txt
katana/native/__init__.py
katana/native/readme.txt
katana/static/__init__.py
katana/static/oss/__init__.py
katana/static/oss/jquery-3.3.1.min.js
katana/static/oss/bootstrap-4.1.3/css/.DS_Store
katana/static/oss/bootstrap-4.1.3/css/bootstrap-grid.css
katana/static/oss/bootstrap-4.1.3/css/bootstrap-grid.css.map
katana/static/oss/bootstrap-4.1.3/css/bootstrap-grid.min.css
katana/static/oss/bootstrap-4.1.3/css/bootstrap-grid.min.css.map
katana/static/oss/bootstrap-4.1.3/css/bootstrap-reboot.css
katana/static/oss/bootstrap-4.1.3/css/bootstrap-reboot.css.map
katana/static/oss/bootstrap-4.1.3/css/bootstrap-reboot.min.css
katana/static/oss/bootstrap-4.1.3/css/bootstrap-reboot.min.css.map
katana/static/oss/bootstrap-4.1.3/css/bootstrap.css
katana/static/oss/bootstrap-4.1.3/css/bootstrap.css.map
katana/static/oss/bootstrap-4.1.3/css/bootstrap.min.css
katana/static/oss/bootstrap-4.1.3/css/bootstrap.min.css.map
katana/static/oss/bootstrap-4.1.3/js/bootstrap.bundle.js
katana/static/oss/bootstrap-4.1.3/js/bootstrap.bundle.js.map
katana/static/oss/bootstrap-4.1.3/js/bootstrap.bundle.min.js
katana/static/oss/bootstrap-4.1.3/js/bootstrap.bundle.min.js.map
katana/static/oss/bootstrap-4.1.3/js/bootstrap.js
katana/static/oss/bootstrap-4.1.3/js/bootstrap.js.map
katana/static/oss/bootstrap-4.1.3/js/bootstrap.min.js
katana/static/oss/bootstrap-4.1.3/js/bootstrap.min.js.map
katana/static/oss/css/bootstrap.min.css
katana/static/oss/css/jstree/32px.png
katana/static/oss/css/jstree/40px.png
katana/static/oss/css/jstree/jstree.min.css
katana/static/oss/css/jstree/throbber.gif
katana/static/oss/fontawesome-5.5.0/LICENSE.txt
katanaframework-1.0.0.dist-info/AUTHORS
katanaframework-1.0.0.dist-info/LICENSE
katanaframework-1.0.0.dist-info/METADATA
katanaframework-1.0.0.dist-info/WHEEL
katanaframework-1.0.0.dist-info/top_level.txt
katanaframework-1.0.0.dist-info/RECORD
