Metadata-Version: 2.1
Name: katanaframework
Version: 1.0.0
Summary: Katana Framework is an open source Automation Framework
Home-page: https://github.com/warriorframework/Katanaframework
Author: warriorteam
Author-email: frameworkwarrior@gmail.com
License: UNKNOWN
Project-URL: Documentation, http://warriorframework.org/
Project-URL: Source Code, https://github.com/warriorframework/Katanaframework
Platform: UNKNOWN
Classifier: Development Status :: 5 - Production/Stable
Classifier: License :: OSI Approved :: Apache Software License
Classifier: Programming Language :: Python :: 3.6
Requires-Dist: requests (==2.21.0)
Requires-Dist: Django (==2.1.2)
Requires-Dist: xmltodict (==0.12.0)
Requires-Dist: python-ldap
Requires-Dist: django-auth-ldap
Requires-Dist: djangorestframework (==3.10.3)
Requires-Dist: gcg (==0.2.0)
Requires-Dist: termcolor (==1.1.0)
Requires-Dist: cryptography (==2.9.2)
Requires-Dist: psycopg2 (==2.8.5)
